gdocrevisions/__init__.py
gdocrevisions/document.py
gdocrevisions/element.py
gdocrevisions/operation.py
gdocrevisions/replay.py
gdocrevisions/revision.py
gdocrevisions/session.py
gdocrevisions/suboperation.py
gdocrevisions/timeddoc.py
gdocrevisions-1.0.1.dist-info/DESCRIPTION.rst
gdocrevisions-1.0.1.dist-info/METADATA
gdocrevisions-1.0.1.dist-info/RECORD
gdocrevisions-1.0.1.dist-info/WHEEL
gdocrevisions-1.0.1.dist-info/metadata.json
gdocrevisions-1.0.1.dist-info/top_level.txt
